Metadata-Version: 2.1
Name: multiformats
Version: 0.3.1.post4
Summary: Python implementation of multiformats protocols.
Home-page: https://github.com/hashberg-io/multiformats
Author: hashberg
Author-email: sg495@users.noreply.github.com
Project-URL: Bug Tracker, https://github.com/hashberg-io/multiformats/issues
Classifier: Development Status :: 3 - Alpha
Classifier: Programming Language :: Python :: 3.12
Classifier: Programming Language :: Python :: 3.11
Classifier: Programming Language :: Python :: 3.10
Classifier: Programming Language :: Python :: 3.9
Classifier: Programming Language :: Python :: 3.8
Classifier: Programming Language :: Python :: 3.7
Classifier: Operating System :: OS Independent
Classifier: Natural Language :: English
Classifier: Typing :: Typed
Requires-Python: >=3.7
License-File: LICENSE
Requires-Dist: typing-extensions>=4.6.0
Requires-Dist: typing-validation>=1.1.0
Requires-Dist: bases>=0.3.0
Requires-Dist: multiformats-config>=0.3.0
Provides-Extra: dev
Requires-Dist: mypy; extra == "dev"
Requires-Dist: pylint; extra == "dev"
Requires-Dist: pytest; extra == "dev"
Requires-Dist: pytest-cov; extra == "dev"
Requires-Dist: blake3; extra == "dev"
Requires-Dist: pyskein; extra == "dev"
Requires-Dist: mmh3; extra == "dev"
Requires-Dist: pycryptodomex; extra == "dev"
Requires-Dist: rich; extra == "dev"
Provides-Extra: full
Requires-Dist: blake3; extra == "full"
Requires-Dist: pyskein; extra == "full"
Requires-Dist: mmh3; extra == "full"
Requires-Dist: pycryptodomex; extra == "full"
Requires-Dist: rich; extra == "full"
